examples/__init__.py
examples/fashion_MNIST.py
examples/genetic_finance.py
examples/random_XOR.py
lucidmode/__init__.py
lucidmode/convolution.py
lucidmode/functions.py
lucidmode/models.py
lucidmode/optimizers.py
lucidmode/propagate.py
lucidmode/regularization.py
lucidmode/learning/__init__.py
lucidmode/learning/dojo.py
lucidmode/learning/execution.py
lucidmode/tools/__init__.py
lucidmode/tools/io_data.py
lucidmode/tools/metrics.py
lucidmode/tools/processing.py
lucidmode/tools/visualizations.py
lucidmode-0.4.3.12.dist-info/LICENSE
lucidmode-0.4.3.12.dist-info/METADATA
lucidmode-0.4.3.12.dist-info/WHEEL
lucidmode-0.4.3.12.dist-info/top_level.txt
lucidmode-0.4.3.12.dist-info/RECORD
