Metadata-Version: 2.1
Name: lucidmode
Version: 0.4.3.12
Summary: Interpretable Machine Learning Models
Home-page: https://github.com/lucidmode/lucidmode
Author: IFFranciscoME
Author-email: if.francisco.me@gmail.com
License: UNKNOWN
Platform: UNKNOWN
Classifier: Development Status :: 4 - Beta
Classifier: License :: OSI Approved :: GNU General Public License v3 (GPLv3)
Classifier: Intended Audience :: Science/Research
Classifier: Intended Audience :: Developers
Classifier: Programming Language :: Python :: 3
Classifier: Programming Language :: Python :: 3.8
Classifier: Operating System :: Unix
Classifier: Operating System :: Microsoft :: Windows
Classifier: Operating System :: MacOS
Classifier: Topic :: Scientific/Engineering :: Artificial Intelligence
Classifier: Topic :: Scientific/Engineering :: Visualization
Requires-Python: >=3.6.0
Requires-Dist: matplotlib
Requires-Dist: numpy
Requires-Dist: pandas
Requires-Dist: plotly
Requires-Dist: rich
Requires-Dist: seaborn
